8bit-alu/alu.v
module alu(input [7:0]a,b, input [2:0]op, output reg [7:0]out, output reg zero_f, carry_f, negative_f, overflow_f);
reg [8:0]temp;
always @(*)begin
    carry_f=0;
    overflow_f=0;
    case(op)
    3'b000: begin
        temp=a+b;
        out=temp[7:0];
        carry_f=temp[8];
    end
    3'b001: begin
        temp=a-b;
        out=temp[7:0];
        carry_f=temp[8];
    end
    3'b010: out=a&b;
    3'b011: out=a|b;
    3'b100: out=a^b;
    3'b101: out=~a;
    3'b110: out=a<<1;
    3'b111: out=a>>1;
    endcase
    zero_f=(out==8'b00000000);
    negative_f=out[7];              // if MSB is 1 then the number is negative
end
endmodule

alu_tb.v
module alu_tb;
reg [7:0]a;
reg [7:0]b;
reg [2:0]op;

wire [7:0]out;
wire zero_f,carry_f,negative_f,overflow_f;

alu uut(.a(a),.b(b),.op(op),.out(out),.zero_f(zero_f),.carry_f(carry_f),.negative_f(negative_f),.overflow_f(overflow_f));
initial begin 
    $dumpfile("wave.vcd");
    $dumpvars(0, alu_tb);
    a=8'd10; b=8'd5; 
    op=3'b000; #10;
    op=3'b001; #10;
    op=3'b010; #10;
    op=3'b011; #10;
    op=3'b100; #10;
    op=3'b101; #10;
    op=3'b110; #10;
    op=3'b111; #10;

    $finish; 
end
endmodule

wave.vcd
$date
	Fri Mar 13 01:55:05 2026
$end
$version
	Icarus Verilog
$end
$timescale
	1s
$end
$scope module alu_tb $end
$var wire 1 ! zero_f $end
$var wire 1 " overflow_f $end
$var wire 8 # out [7:0] $end
$var wire 1 $ negative_f $end
$var wire 1 % carry_f $end
$var reg 8 & a [7:0] $end
$var reg 8 ' b [7:0] $end
$var reg 3 ( op [2:0] $end
$scope module uut $end
$var wire 8 ) a [7:0] $end
$var wire 8 * b [7:0] $end
$var wire 3 + op [2:0] $end
$var reg 1 % carry_f $end
$var reg 1 $ negative_f $end
$var reg 8 , out [7:0] $end
$var reg 1 " overflow_f $end
$var reg 9 - temp [8:0] $end
$var reg 1 ! zero_f $end
$upscope $end
$upscope $end
$enddefinitions $end
$comment Show the parameter values. $end
$dumpall
$end
#0
$dumpvars
b1111 -
b1111 ,
b0 +
b101 *
b1010 )
b0 (
b101 '
b1010 &
0%
0$
b1111 #
0"
0!
$end
#10
b101 #
b101 ,
b101 -
b1 (
b1 +
#20
1!
b0 #
b0 ,
b10 (
b10 +
#30
0!
b1111 #
b1111 ,
b11 (
b11 +
#40
b100 (
b100 +
#50
1$
b11110101 #
b11110101 ,
b101 (
b101 +
#60
0$
b10100 #
b10100 ,
b110 (
b110 +
#70
b101 #
b101 ,
b111 (
b111 +
